foliant/cli/notifier.py
foliantcontrib.notifier-1.0.0.dist-info/LICENSE
foliantcontrib.notifier-1.0.0.dist-info/METADATA
foliantcontrib.notifier-1.0.0.dist-info/WHEEL
foliantcontrib.notifier-1.0.0.dist-info/top_level.txt
foliantcontrib.notifier-1.0.0.dist-info/RECORD
